{
    "type": "FeatureCollection",
    "name": "aree_di_saggio_TEBAKA_punti_28042022_v02_geom",
    "crs": {
        "type": "name",
        "properties": {
            "name": "urn:ogc:def:crs:OGC:1.3:CRS84"
        }
    },
    "features": [
        {
            "type": "Feature",
            "properties": {
                "Cluster": 1,
                "Zona": "Zeuli_Olivo",
                "Id_plot": 152,
                "Id_name": "Zeuli_Olivo_cluster_1_idPlot_152"
            },
            "geometry": {
                "type": "Point",
                "coordinates": [
                    16.190746200350443,
                    41.238583788
                ]
            }
        }
    ]
}